Workbook
Name \A: #REF!
Name \A: #REF!
Name _: '[1]046 Fixed Ass. mov.'!#REF!
Name __PC1: '[2]Physical Count'!$A$1:$B$65536
Name _CRA: [3]U40!#REF!
Name _CRA: [3]U40!#REF!
Name _DAT5: [4]SFG_ND!#REF!
Name _DAT7: [4]SFG_ND!#REF!
Name _DAT8: [4]SFG_ND!#REF!
Name _ftn1: '3 分部财务数据'!#REF!
Name _ftn2: 行业情况!$B$9
Name _ftn3: 行业情况!$B$10
Name _ftnref1: '3 分部财务数据'!#REF!
Name _ftnref2: 行业情况!$B$2
Name _ftnref3: 行业情况!$B$3
Name _Toc106357774: 行业情况!$B$6
Name _W_DMOP_Billing_report_Jul_02: #REF!
Name A: #REF!
Name A: #REF!
Name aa: #REF!
Name aaa: #REF!
Name ACCOUNT: [5]Bank!$C$2:$C$99
Name AccountDesc: [6]Accounts!$A$1:$A$386
Name APTTL: [7]BKD!$N$573
Name AR: #REF!
Name AR: #REF!
Name AR_Summary_SGD_Currency: #REF!
Name AR_Summary_SGD_Currency: #REF!
Name AR_Summary_Source_Currency: #REF!
Name AR_Summary_Source_Currency: #REF!
Name ARUTL: #REF!
Name ARUTL: #REF!
Name as: [8]Input!$D$4
Name Automobiles: #REF!
Name b: #REF!
Name b: #REF!
Name brec0396: [9]jun94!#REF!
Name building: #REF!
Name Category: #REF!
Name Category: #REF!
Name CC: #REF!
Name CLIENT_NAME: #REF!
Name CNAME: [5]Bank!$B$2:$B$99
Name COA: #REF!
Name cost1: [2]Cost!$A$1:$P$65536
Name Cr: #REF!
Name Custom1: '[10]Drill-Down Lists'!$H$2:$H$3
Name Custom2: '[10]Drill-Down Lists'!$I$2:$I$544
Name Custom3: '[10]Drill-Down Lists'!$J$2:$J$3
Name Custom4: '[10]Drill-Down Lists'!$K$2:$K$3
Name Customer_Master_File: #REF!
Name Customer_Master_File: #REF!
Name CYCLES: [11]JobDetails!$A$56:$A$90
Name dfd: #REF!
Name Doubt_Debt: #REF!
Name Doubt_Debt: #REF!
Name Dr: #REF!
Name e: #REF!
Name e_data: OFFSET(#REF!,1,0,COUNTA(#REF!)-1,2)
Name e_empindex: #REF!

Sheet 数据表
A1: 企业名称 | B1: ='1 组织结构及管理架构'!A1 -> 上海派智能源股份有限公司
A2: 年度 | B2: =RIGHT(LEFT('3 分部财务数据'!A5,12),2) -> 23
A3: 事务所名称 | B3: =资料清单!A5 -> 立信税务师事务所有限公司
A4: 事务所简称 | B4: =资料清单!A6 -> 立信税务
A5: 企业简称 | B5: =资料清单!A7 -> 派智能源
A6: 母公司全称 | B6: =资料清单!A8 -> 0
A7: 集团情况描述 | B7: =集团背景情况!A1 -> 派智能源是以锂电池制造为基础的高科技企业，公司始创于2004年，经过19年的行业积淀。公司已经发展布局了：总部上海派智，山东派智电子，越南派智以及山东派智新能源4个主要工厂。在境外成立了美国和荷兰子公司，同时2022年在匈牙利新设立了锂电池生产线。公司目前全球员工约1000名，年产能1.82Gwh。 业务涵盖3C、智能吸尘器、电动自行车、电动摩托车、储能等多个领域，致力于为全球客户带来先进的能源解决方案。
A8: 公司经营背景资料 | B8: =公司经营背景资料!A1 -> 上海派智成立于2015年02月09日，经营期限为无固定期限。公司主要从事锂电池相关的研发及制造。截至2023年12月31日，公司注册资本为人民币9,415万元。经营地址上海市奉贤区青村镇光明金钱公路3492号第9幢，经营期限无固定期限。注册资本 （截至2023年12月31日）为人民币9,415万元。主要经营活动包括许可项目：货物进出口；技术进出口。（依法须经批准的项目，经相关部门批准后方可开展经营活动，具体经营项目以相关部门批准文件或许可证件为准）一般项目：一般项目：新兴能源技术研发；新能源汽车电附件销售；新能源原动设备销售；技术服务、技术开发、技术咨询、技术交流、技术转让、技术推广（人体干细胞、基因诊断与治疗技术开发和应用除外）；电池销售；电池制造；电池研发；电动自行车销售；助动车研发；助动车制造；电机及其控制系统研发；光伏设备及元器件制造；光伏设备及元器件销售；光伏设备及元器件研发；集成电路制造；集成电路销售；集成电路研发；互联网销售（除销售需要许可的商品）；电子元器件批发；电子元器件零售。（除依法须经批准的项目外，凭营业执照依法自主开展经营活动）总经办7人，负责全公司的常规运维工作，部门负责人对总经办汇报，汇报对象主要办公地上海。事业部148人，负责事业部经营运维工作，部门负责人对总经办汇报，汇报对象主要办公地上海。财务中心17人，负责公司财务核算分析工作，部门负责人对总经办汇报，汇报对象主要办公地上海。营销中心44人，负责公司产品的销售工作，部门负责人对总经办汇报，汇报对象主要办公地上海。 研发中心2人，负责公司产品的研究开发工作，部门负责人对总经办汇报，汇报对象主要办公地上海。运营中心122人，负责公司产品的生产工作，新供应商 、新物料的采购开发，信息化建设或优化，人员管理及后勤工作，部门负责人对总经办汇报，汇报对象主要办公地上海。总计340人。 评估期间，上海派智从事锂电池制造业务，主营业务收入948,194,916.22元，主营业务成本804,743,968.37元，营业税金及附加3,270,449.93元，销售费用55,298,620.54元，管理费用85,657,237.96元，资产减值损失-1,388,027.19元，总成本947,582,249.61元，息税前利润612,666.61元，完全成本加成率0.06%主营业务收入948,194,916.22元，主营业务成本804,743,968.37元，营业税金及附加3,270,449.93元，销售费用55,298,620.54元，管理费用85,657,237.96元，资产减值损失-1,388,027.19元，总成本947,582,249.61元，息税前利润612,666.61元，完全成本加成率0.06%主营业务收入948,194,916.22元，主营业务成本804,743,968.37元，营业税金及附加3,270,449.93元，销售费用55,298,620.54元，管理费用85,657,237.96元，资产减值损失-1,388,027.19元，总成本947,582,249.61元，息税前利润612,666.61元，完全成本加成率0.06%。上海派智在2023年度不仅进行生产与销售业务，同时还向第三方客户销售其从第三方采购的原材料（“第三方原料分销”），金额为267,037,913.78元。由于上述第三方原料分销业务与关联交易无关，而其与关联方的业务往来均与其的生产销售业务活动密切相关且不可分割。因此，我们主要对其生产销售业务相关（即受测关联交易）的财务数据进行分析和验证，具体参见章节7.4.2的确定与受测关联交易相关的财务数据。

Sheet 集团背景情况
A1: 派智能源是以锂电池制造为基础的高科技企业，公司始创于2004年，经过19年的行业积淀。公司已经发展布局了：总部上海派智，山东派智电子，越南派智以及山东派智新能源4个主要工厂。在境外成立了美国和荷兰子公司，同时2022年在匈牙利新设立了锂电池生产线。公司目前全球员工约1000名，年产能1.82Gwh。 业务涵盖3C、智能吸尘器、电动自行车、电动摩托车、储能等多个领域，致力于为全球客户带来先进的能源解决方案。

Sheet 公司经营背景资料
A1: 上海派智成立于2015年02月09日，经营期限为无固定期限。公司主要从事锂电池相关的研发及制造。截至2023年12月31日，公司注册资本为人民币9,415万元。经营地址上海市奉贤区青村镇光明金钱公路3492号第9幢，经营期限无固定期限。注册资本 （截至2023年12月31日）为人民币9,415万元。主要经营活动包括许可项目：货物进出口；技术进出口。（依法须经批准的项目，经相关部门批准后方可开展经营活动，具体经营项目以相关部门批准文件或许可证件为准）一般项目：一般项目：新兴能源技术研发；新能源汽车电附件销售；新能源原动设备销售；技术服务、技术开发、技术咨询、技术交流、技术转让、技术推广（人体干细胞、基因诊断与治疗技术开发和应用除外）；电池销售；电池制造；电池研发；电动自行车销售；助动车研发；助动车制造；电机及其控制系统研发；光伏设备及元器件制造；光伏设备及元器件销售；光伏设备及元器件研发；集成电路制造；集成电路销售；集成电路研发；互联网销售（除销售需要许可的商品）；电子元器件批发；电子元器件零售。（除依法须经批准的项目外，凭营业执照依法自主开展经营活动）总经办7人，负责全公司的常规运维工作，部门负责人对总经办汇报，汇报对象主要办公地上海。事业部148人，负责事业部经营运维工作，部门负责人对总经办汇报，汇报对象主要办公地上海。财务中心17人，负责公司财务核算分析工作，部门负责人对总经办汇报，汇报对象主要办公地上海。营销中心44人，负责公司产品的销售工作，部门负责人对总经办汇报，汇报对象主要办公地上海。 研发中心2人，负责公司产品的研究开发工作，部门负责人对总经办汇报，汇报对象主要办公地上海。运营中心122人，负责公司产品的生产工作，新供应商 、新物料的采购开发，信息化建设或优化，人员管理及后勤工作，部门负责人对总经办汇报，汇报对象主要办公地上海。总计340人。 评估期间，上海派智从事锂电池制造业务，主营业务收入948,194,916.22元，主营业务成本804,743,968.37元，营业税金及附加3,270,449.93元，销售费用55,298,620.54元，管理费用85,657,237.96元，资产减值损失-1,388,027.19元，总成本947,582,249.61元，息税前利润612,666.61元，完全成本加成率0.06%主营业务收入948,194,916.22元，主营业务成本804,743,968.37元，营业税金及附加3,270,449.93元，销售费用55,298,620.54元，管理费用85,657,237.96元，资产减值损失-1,388,027.19元，总成本947,582,249.61元，息税前利润612,666.61元，完全成本加成率0.06%主营业务收入948,194,916.22元，主营业务成本804,743,968.37元，营业税金及附加3,270,449.93元，销售费用55,298,620.54元，管理费用85,657,237.96元，资产减值损失-1,388,027.19元，总成本947,582,249.61元，息税前利润612,666.61元，完全成本加成率0.06%。上海派智在2023年度不仅进行生产与销售业务，同时还向第三方客户销售其从第三方采购的原材料（“第三方原料分销”），金额为267,037,913.78元。由于上述第三方原料分销业务与关联交易无关，而其与关联方的业务往来均与其的生产销售业务活动密切相关且不可分割。因此，我们主要对其生产销售业务相关（即受测关联交易）的财务数据进行分析和验证，具体参见章节7.4.2的确定与受测关联交易相关的财务数据。

Sheet 行业情况
A1: 3.1. 行业概述 | B1: 锂离子电池是一种二次电池（充电电池），它主要依靠锂离子在正极和负极之间移动来工作。近年来，锂电池不仅广泛应用于新能源汽车、消费类电子产品、储能领域，而且受工业智能化、军事信息化、民用便利化以及互联网、物联网、智慧城市快速发展带动，应用场景日趋丰富、产品质量持续提升。 根据高工锂电产业研究所（GGII）不完全统计，2023年中国锂电池及四大主材（不含铜箔、结构件等辅材）共有137个新增规划项目（只统计公告/签约项目，以下分析均指该数据），较2022年减少近一半。按公布投资金额的122个项目进行统计，2023年中国锂电产业拟投资总额约7500亿元，较2022年下降超46%，尤其是负极材料项目，新签约项目投资额仅为去年的18%。 根据前瞻产业研究院《2024年中国动力锂电池行业投融资现状及兼并重组分析 投融资热度下滑》，2015-2023年，我国动力锂电池行业融资事件数和金额呈波动趋势，融资事件数2022年达到顶点，为48起，融资金额2021年达到顶点，为409.2亿元。整体来看，2016年以来，我国动力锂电池行业融资事件数和金额均处于较高水平，我国动力锂电池行业融资较热。但2023年，我国动力锂电池行业融资事件数和融资金额均下降，分别为27起和139.4亿元，融资热度有所下滑。尽管2022年和2023年的融资金额和事件数有所下降，但仍然保持在较高水平，表明市场对锂电产业的关注度依然较高，但经过前几年的高速增长后逐步步入相对稳定的发展阶段。 图表 7:2015-2023年中国动力锂电池行业融资整体情况（单位：亿元）
A2: 3.2. 行业规模 | B2: 3.2.1全球锂电池行业规模 从全球锂电池出货量情况来看，根据研究机构EVTank、伊维经济研究院联合中国电池产业研究院共同发布了《中国锂离子电池行业发展白皮书(2024年)》数据显示，2023年，全球锂离子电池总体出货量1202.6GWh，同比增长25.6%，增幅相对于2022年已经呈现大幅度下滑。 图表 8：2014年-2023年全球锂电子出货量 从出货结构来看，2023年，全球汽车动力电池（EV LIB）出货量为865.2GWh，同比增长26.5%；储能电池（ESS LIB）出货量224.2GWh，同比增长40.7%；小型电池（SMALL LIB）出货量113.2GWh，同比下滑0.9%。 图表 9：2023年全球锂电池行业出货量结构占比情况 3.2.2中国锂电池行业规模 近年来，中国锂电池出货量不断增长。中商产业研究院发布的《2023-2028年中国锂电池行业市场前景预测及未来发展趋势研究报告》显示，2023年，中国锂离子电池出货量达到887.4GWh，同比增长34.3%，在全球锂离子电池总体出货量的占比达到73.8%，出货量占比继续提升。中商产业研究院分析师预测，2024年中国锂电池出货量将超过1000GWh。 图表 10：2019-2024中国锂电池出货量预测趋势图 2023年我国锂离子电池产业延续增长态势，根据锂电池行业规范公告企业信息和行业协会测算，全国锂电池总产量超过940GWh，同比增长25%，行业总产值超过1.4万亿元。 图表 11：2018年-2023年我国锂离子电池行业规模及增速 从2015年到2023年间，全国锂离子电池行业规模实现逐年攀升。虽然个别年份出现增长波动，但总体来看，中国锂电池行业的增长仍然非常迅速，正迈入行业发展的快车道。 另一方面，新能源汽车市场的持续火爆推动锂离子电池行业快速发展。市场需求逐年攀升，而关于锂离子电池的需求量也在不断增大。新能源汽车作为锂离子电池技术重点应用领域，在低碳环保、技术创新、性能安全上都对其提出了更高的要求。长期来看，锂离子电池行业将形成全产业联动式发展模式，涌现一批技术实力过硬、产业布局能力较强的企业。
A3: 3.3. 行业政策 | B3: 2020年9月22日，我国提出了全面切实做好应对气候变化各项工作的新目标，包括在2060年前实现“碳中和”。此后，政府陆续出台了一系列政策措施，加强碳排放控制和可持续发展等方面的工作，并一直致力于推动全球应对气候变化的协同发展。如减免企业所得税、城市公交、物流车、公务车推广试点等，这些政策为锂电行业带来了巨大的投资机会和市场需求，也推动着锂电技术的进步和发展。 图表 12：锂电池行业相关政策 政策名称 发布部门 相关内容 发布时间 《锂电池行业规范条件(2024年本)》(征求意见稿) 工信部 锂电池企业及项目应符合国家资源开发利用、生态环境保护、节能管理、安全生产等法律法规要求，符合国家产业政策和相关产业规划及布局要求，符合当地国土空间规划和生态环境保护专项规划等要求，符合“三线一单”生态环境分区管控要求。引导企业减少单纯扩大产能的制造项目，加强技术创新、提高产品质量、降低生产成本。 2024年5月 《锂电池行业规范公告管理办法(2024年本)》(征求意见稿) 工信部 引导企业减少单纯扩大产能的制造项目，加强技术创新、提高产品质量、降低生产成本。 2024年5月 《关于加强新能源汽车与电网融合互动的实施意见》 国家发展改革委等部门 加大动力电池关键技术攻关，在不明显增加成本基础上将动力电池循环寿命提升至3000次及以上，攻克高频度双向充放电工况下的电池安全防控技术。 2023年12月 《关于进一步构建高质量充电基础设施体系的指导意见》 国务院 压实电动汽车、动力电池和充电基础设施生产企业产品质量安全责任，严格充电基础设施建设、安装质量安全管理，建立火灾、爆炸事故责任倒查制度。持续优化电动汽车电池技术性能，加强新体系动力电池、电池梯次利用等技术研究。 2023年6月 《关于做好锂离子电池产业链供应链协同稳定发展工作的通知》 工信部、市场监管总局 鼓励锂电池生产商、锂电池材料生产商、上游矿产资源企业、锂电池回收企业等协调配合，共同引导上下游参与者稳定市场期望、明确供需及价格并确保稳定供应。 2022年11月 《科技支撑破达峰碳中和实施方案(2022-2030年)》 科技部、工信部、国家发改委等9部门 力争到2030年，动力电池、驱动电机、车用操作系统等关键技术取得重大突破，新能源汽车安全水平全面提升，纯电动乘用车新车平均电耗大幅下降。 2022年8月 《关于推动轻工业高质量发展的指导意见》 工业和信息化等五部门 指出高能效锂电池安全技术是关键研发技术之一 2022年6月 《关于加强产业融合推动工业绿色发展的指导意见》 工业和信息化等四部门 指出要提升新能源汽车等产业链水平，加快充电桩、换电站等基础设施建设运营，推动新能源汽车动力电池回收利用体系建设 2021年9月 2020年以来，面对电动汽车市场蓬勃发展，锂电产业链上中高端市场的格局被清晰地呈现出来，高新材料的研发、电芯工艺技术的提升、设备制造的创新三个领域成为中国锂电产业下一步发力重点。同时，政府也相继出台扶持新能源产业发展的政策支持，促进锂电产业的升级和转型。 未来，随着技术不断进步，中国锂电行业发展将进入以政策为主导、以技术创新为驱动，逐步拓宽锂离子电池在品质、安全、环保等方面的市场竞争力，迎来更广泛应用空间和发展机会。
A4: 3.4. 市场竞争情况 | B4: 锂离子电池行业具有较高的技术壁垒，经过多年的发展，市场主要的锂离子电池制造商数量相对固定，市场集中度较高，其中，前十大锂离子电池制造商占据全球超过50%的市场份额。 国际上，中国、日本和韩国是全球锂离子电池的主要生产国，三国总产量占比达90%以上。其中，日本主要为松下、索尼，韩国主要为三星SDI、LG化学等。日本松下、索尼等厂商在规模、技术各方面占据主导地位，韩国电子产品迅速崛起，锂离子电池厂商快速成长，目前已是全球领先的锂离子电池生产国。近年来，中国厂商在锂离子电池的产能和技术等方面不断提升，宁德时代、比亚迪、亿纬锂能等陆续崛起，使得中国成为全球锂离子电池生产制造的重要参与者。 经过数年发展，我国锂离子电池行业集中度不断提高。国内主要的锂离子电池企业为宁德时代、比亚迪、亿纬锂能、中创新航、国轩高科、欣旺达、蜂巢能源、孚能科技、鹏辉能源等。国内市场上还有数量众多的中小型厂商，由于自身规模、研发实力不足，不能自主生产电芯，而主要采用进口或外购国内大型厂商电芯来组装生产电池产品。随着行业环保要求的日益严格以及市场对产品技术和质量要求的不断提高，小型企业生存空间将逐步压缩，而行业领先企业将凭借技术、质量、规模和环保治理等优势逐步扩大市场份额，行业集中度将进一步提高。
A5: 3.5. 行业前景预测 | B5: 锂电技术是未来新能源领域的重要技术之一，它不仅具有高能量密度、安全可靠等优点，广泛应用于电动汽车、储能、消费电子等领域，也是未来的主流能源之一。分析来看，锂离子电池行业发展呈现出以下发展态势：  政策利好行业发展 近年来，我国政府相关部门出台了一系列政策，支持锂电池产业的发展。2024年5月工信部对《锂离子电池行业规范条件(2021年本)》《锂离子电池行业规范公告管理办法(2021年本)》进行修订，而形成《锂电池行业规范条件(2024年本)》《锂电池行业规范公告管理办法(2024年本)》(征求意见稿)，本次征求意见稿对锂电企业的产业布局和项目设立、生产经营和工艺水平、产品性能、安全和质量管理等多方面提出了要求。政策的发布为锂电池行业的发展提供了明确、广阔的市场前景，为企业提供了良好的生产经营环境。  技术进步驱动行业发展 随着科技的不断发展，锂电池在材料、工艺、性能以及安全性等方面取得了显著的进步。通过研发新型的正负极材料和电解质，锂电池的能量密度得到了显著提升；优化电池的内部结构，提高电池的效率和寿命；引入智能传感器和云计算等技术，实现对电池的实时监控和预测性维护。在技术进步的推动下，锂电池的应用领域也在不断拓展，新的应用领域为锂电池行业带来了巨大的市场空间和发展机遇。  下游需求增加推动行业发展 随着新能源汽车和储能市场的持续增长，锂电池行业预计将继续保持增长势头，中国已经连续五年成为全球最大的锂电池消费市场，且市场规模仍在不断扩大。得益于新能源汽车产业的发展，市场上对优质动力电池企业的需求不断增加。新能源汽车的高速发展带动锂离子电池需求的增加，目前锂离子动力电池的供应不能满足市场上的相关需求。
A6: 3.6.结论 | B6: 中国作为全球最大锂电池的生产国和市场，拥有巨大的发展潜力。随着电动汽车、储能等领域的不断发展，对锂电池的需求将持续增加。锂电行业近几年在技术和产品发展上进步显著，国内产业链不断优化，设备智能化和工艺水平不断改进，多数锂电制造企业不断加大研发投入，为行业产品更新换代助力。我国的锂电企业通过自主创新和吸收引进相结合的方式，在部分细分领域实现了突破和发展，技术水平不断提升。 目前虽然我国锂电池行业增长率较高，但市场集中度高，导致中小型企业竞争激烈。市场上占据主导地位的大型企业，如宁德时代、比亚迪等，拥有强大的研发能力和雄厚的资金支持，使其在技术创新、生产规模和市场占有率方面占据优势。这些龙头企业能够通过规模效应降低生产成本，提高产品竞争力，并在市场上形成较强的品牌效应。而随着动力电池市场竞争进一步加剧，龙头企业优势不断放大，行业集中度持续提升。 因此，中小型企业在这种高市场集中度的环境中面临着诸多挑战。首先是资金和资源的限制，这使得它们在技术研发和规模扩展上处于劣势。其次，大型企业在供应链管理和客户资源方面具有更强的控制力，使得中小型企业难以在市场上获得稳定的原材料供应和客户订单。 总的来说，随着技术的进步和政策的支持，预计中国锂电池产业将继续保持快速增长，并在全球锂电池市场中发挥重要作用。但由于激烈的竞争环境，上海派智的发展也面临着一些挑战。

Sheet 被测关联交易
A1: 被测关联交易利润水平 | B1: 0.0373
B2: 完全成本加成率

Sheet 资料清单
A1: 【年度】年度转让定价同期资料准备所需基础资料和文件清单
A4: 敬请注意，该“提供资料清单”只适用于上海派智能源股份有限公司（以下简称“贵公司”）。贵公司需要提供截至2023会计年度12月31日（以下简称“2023年度”）的信息与资料，敬请贵公司注意，该清单是基于本所目前对贵公司经营状况的理解，该“资料清单”并不是全面的或是最终的，必要时我们会继续要求贵公司提供额外的信息和资料。 我们希望贵公司能够尽量以电子表格的形式提供数据。对于较难获得或者以现场讨论的方式更易获取的信息，我们将在访谈时与贵公司进行探讨。如果贵公司有任何的问题或建议，请联系我们的团队成员： Director: Lillian Deng Email: deng.chengyu@bdo.com.cn Manager: Zoe Li Email: li.shuyi@bdo.com.cn
A5: 立信税务师事务所有限公司
A6: 立信税务
A7: 派智能源
A9: 资料清单 | B9: 附注
A10: I. 基本信息
A11: 1. 中华人民共和国企业法人营业执照 | B11: 如有更新请提供
A12: 2. 组织结构，包括企业各职能部门的设置、职责范围和雇员数量等（请提供截至【年度】年12月31日时点的组织结构图） | B12: 请见附件1
A13: 3. 管理架构，包括企业各级管理层的汇报对象以及汇报对象主要办公所在地等（请提供截至【年度】年12月31日时点的信息）
A14: 4. 【年度】年度关联公司信息 | B14: 请见附件2
A15: II. 财务信息
A16: 1. 【年度】年审计报告，包括经审计的财务报表及其附注 | B16: 请提供
A17: 2. 【年度】年度分部财务数据分析表，需包括企业不同类型产品的收入、成本、费用及利润。 | B17: 请见附件3
A18: 3. 【年度】年度《中华人民共和国企业年度关联业务往来报告表(2016年版)》 | B18: 请提供电子版
A19: 4. 【年度】年度贵公司主要关联供应商名单 | B19: 请见附件4
A20: 5. 【年度】年度的主要关联客户清单 | B20: 请见附件5
A21: 6. 【年度】年度其他关联交易类型、金额（如涉及） | B21: 如涉及，请提供

Sheet 1 组织结构及管理架构
A1: 上海派智能源股份有限公司
A3: 附件一：组织结构及管理架构
A4: 以下内容根据贵公司2022年度资料清单中提供的相关信息预填，请贵公司就2023年度情况对以下描述进行确认或更新。
A5: 请更新截至2023年12月31日公司组织架构情况
A6: 部门 | C6: 人数 （截至2023年12月31日） | D6: 主要职责范围简介 | E6: 部门负责人汇报对象 | F6: 部门负责人汇报对象主要办公所在地
A7: LEV事业部 | C7: 72 | D7: 1、总经理应向公司集团领导负责，全面组织实施集团领导会的有关决议和规定，全面完成集团领导下达的各项指标，并将实施情况向集团领导汇报； 2、负责宣传贯彻执行国家和行业有关法律、法规、方针、政策； 3、根据集团的要求确定公司的经营方针，建立公司的经营管理体系并组织实施和改进，为经营管理体系运行提供足够的资源； 4、主持公司的日常各项经营管理工作，组织实施公司年度经营计划； 5、根据市场变化，不断调整公司的经营方向，使公司持续健康发展； 6、负责倡导公司的企业文化和经营理念，塑造企业形象； 7、负责代表公司对外处理业务，开展公关活动； 8、负责公司信息管理系统的建立及信息资源的配置； 9、签署日常行政、业务文件，保证公司经营运作的合法性； 10、负责公司人力资源的开发、管理和提高； 11、负责公司安全工作； 12、负责确定公司的年度财务预、决算方案，利润分配方案和弥补亏损方案； 13、负责公司组织结构的调整； 14、负责组织完成集团下达的其它临时性、阶段性工作和任务。 | E7: 吕振国 | F7: 上海
A8: 储能事业部 | C8: 53 | D8: 1、总经理应向公司集团领导负责，全面组织实施集团领导会的有关决议和规定，全面完成集团领导下达的各项指标，并将实施情况向集团领导汇报； 2、负责宣传贯彻执行国家和行业有关法律、法规、方针、政策； 3、根据集团的要求确定公司的经营方针，建立公司的经营管理体系并组织实施和改进，为经营管理体系运行提供足够的资源； 4、主持公司的日常各项经营管理工作，组织实施公司年度经营计划； 5、根据市场变化，不断调整公司的经营方向，使公司持续健康发展； 6、负责倡导公司的企业文化和经营理念，塑造企业形象； 7、负责代表公司对外处理业务，开展公关活动； 8、负责公司信息管理系统的建立及信息资源的配置； 9、签署日常行政、业务文件，保证公司经营运作的合法性； 10、负责公司人力资源的开发、管理和提高； 11、负责公司安全工作； 12、负责确定公司的年度财务预、决算方案，利润分配方案和弥补亏损方案； 13、负责公司组织结构的调整； 14、负责组织完成集团下达的其它临时性、阶段性工作和任务。 | E8: 吕振国 | F8: 上海
A9: 消费类电子事业部 | C9: 23 | D9: 1、负责针对公司的经营目标，分解事业处经营指标，并推进实施； 2、不断调整优化经营管理细节，对事业处的经营指标最终负责； 3、负责事业处管理团队的策划/搭建； 4、负责事业处培训体系、能力矩阵的规划/实施； 5、负责事业处人才梯队的构建； 6、负责事业处的日常事务管理； 7、负责事业处考评、薪酬体系的搭建/管理； 8、事业处的整体经营风险和机遇评估，及执行相应的措施以规避或者降低风险； 9、了解ISO9001&ISO14001管理体系知识，熟悉管理方针和目标；维护、推动事业处管理体系的有效运行。 10、负责组织完成集团下达的其它临时性、阶段性工作和任务。 | E9: 吕振国 | F9: 上海
A10: 第一营销中心 | C10: 19 | D10: 1．总经理应向公司集团领导负责，全面组织实施集团领导会的有关决议和规定，全面完成集团领导下达的各项指标，并将实施情况向集团领导汇报； 2．负责宣传贯彻执行国家和行业有关法律、法规、方针、政策； 3．根据集团的要求确定公司的经营方针，建立公司的经营管理体系并组织实施和改进，为经营管理体系运行提供足够的资源； 4．主持公司的日常各项经营管理工作，组织实施公司年度经营计划； 5．根据市场变化，不断调整公司的经营方向，使公司持续健康发展； 6．负责倡导公司的企业文化和经营理念，塑造企业形象； 7．负责代表公司对外处理业务，开展公关活动； 8 负责公司信息管理系统的建立及信息资源的配置； 9 签署日常行政、业务文件，保证公司经营运作的合法性； 10 负责公司人力资源的开发、管理和提高； 11 负责公司安全工作； 12 负责确定公司的年度财务预、决算方案，利润分配方案和弥补亏损方案； 13 负责公司组织结构的调整； 14 负责组织完成集团下达的其它临时性、阶段性工作和任务。 | E10: 吕振国 | F10: 上海
A11: 第二营销中心 | C11: 18 | D11: 1、 负责部门发展、定位的策划； 2、 负责管理销售经理和业务员； 2、市场的开发及客户的维护与服务； 3、客户订单及单据的审核与控制；组织客户合同、协议评审； 4、负责部门销售业绩及销售目标的制定执行； 5、负责市场信息的收集及竞争对手的分析，协助完成市场调查分析报告； 6、统筹识别本部门的风险和机遇，并定期参与评审及执行相应的管理措施以规避或者降低风险级别； 7、了解本部门的环境因素、重要环境因素清单，制定本部门重要环境因素的管理方法； 8、统筹维护并保证本部门管理体系（ISO9001/ISO14001）正常、有效的运行； 9、统筹管理本部门的日常工作； 10、完成其他相关事项。 | E11: 吕振国 | F11: 上海
A12: 第三营销中心 | C12: 4 | D12: 目的：为实现公司东欧区域营销目标，具体组织并落实公司持续健康发展，全面完成集团领导下达的各项中东亚营销指标任务，及其他部分的建立和完善发展工作 1、组织实施第三营销中心工作：组织实施公司年度经营计划；全面完成集团领导下达的各项指标，并将实施情况向集团领导汇报；全面组织实施集团领导会的有关决议和规定； 2、组织实施公司发展经营方针：总经理应向公司集团领导负责，主持第三营销中心的日常各项经营管理工作，建立公司的经营管理体系并组织实施和改进，为经营管理体系运行提供足够的资源；根据市场变化，不断调整公司的经营方向，使公司持续健康发展；负责代表公司对外处理业务，开展公关活动；负责确定公司的年度财务预、决算方案，利润分配方案和弥补亏损方案； 3、组织负责公司经营工作任务：组织负责公司信息管理系统的建立及信息资源的配置；签署日常行政、业务文件，保证公司经营运作的合法性；负责公司人力资源的开发、管理和提高；负责公司组织结构的调整；负责组织完成公司下达的其它临时性、阶段性工作和任务。 4、宣传贯彻公司安全工作及企业文化建设：负责宣传贯彻执行国家和行业有关法律、法规、方针、政策；负责倡导公司的企业文化和经营理念，塑造企业形象； | E12: 吕振国 | F12: 上海
A13: 第五营销中心 | C13: 3 | D13: 目的：为实现公司中东亚营销目标，具体组织并落实公司持续健康发展，全面完成集团领导下达的各项中东亚营销指标任务，及其他部分的建立和完善发展工作 1、组织实施中东亚营销工作：组织实施公司年度经营计划；全面完成集团领导下达的各项指标，并将实施情况向集团领导汇报；全面组织实施集团领导会的有关决议和规定； 2、组织实施中东亚发展经营方针：总经理应向公司集团领导负责，主持中东亚的日常各项经营管理工作，建立公司的经营管理体系并组织实施和改进，为经营管理体系运行提供足够的资源；根据市场变化，不断调整公司的经营方向，使公司持续健康发展；负责代表公司对外处理业务，开展公关活动；负责确定公司的年度财务预、决算方案，利润分配方案和弥补亏损方案； 3、组织负责公司经营工作任务：组织负责公司信息管理系统的建立及信息资源的配置；签署日常行政、业务文件，保证公司经营运作的合法性；负责公司人力资源的开发、管理和提高；负责公司组织结构的调整；负责组织完成公司下达的其它临时性、阶段性工作和任务。 4、宣传贯彻公司安全工作及企业文化建设：负责宣传贯彻执行国家和行业有关法律、法规、方针、政策；负责倡导公司的企业文化和经营理念，塑造企业形象； | E13: 吕振国 | F13: 上海
A14: 总经办 | C14: 7 | D14: 1、参与内部事务及提供法律保障 （1）参与公司的投资并购、产权转让、招投标及重组等重大经济活动的决策，并处理有关法律事务； （2）向公司业务部门、下属公司提供有关法律咨询； （3）为各部门提供法律咨询，确保各项流程符合法律法规。 2、完善法律风险管理 （1）及时完成合同起草或审核，防范风险、维护公司利益、规范管理； （2）加强员工法律意思的培养，严格遵守相关法律和各项规章制度； （3）做好公司各类案件的诉讼和应诉工作，降低公司因仲裁、诉讼而产生的损失； （4）加强公司内部法律事务管理人员培养，结合本公司的特点和实际情况建立适合的法律风险防范体系； （5）配合业务和财务做好应收账款的催收工作； （6）知识产权管理工作，培养/招聘专门的知识产权管理人员，负责知识产权工作的开展； 3、外联工作 代表公司联络公检法机关和律师事务所，与相关部门建立良好关系； 4、内审体系建设：负责公司内控体系、风险管理体系的构建与维护； 5、风险管理：负责建立并维护风险管理矩阵，定期开展风险识别、风险评价、风险管理。负责推进公司全面风险管理体系建设，形成《内控管理手册》； 6、内审测评：定期开展内审测评，出具年度《内部控制自我评价报告》； 内审缺陷整改：负责推动公司各事业处、中心对内控缺陷事项进行整改； 内审环境优化：负责开展各类内控与风险管理知识宣导，提升公司全员内控与风险管理意识； | E14: 吕振国 | F14: 上海
A15: 财务中心 | C15: 17 | D15: 1、服从公司CEO的统一指挥,认真执行其工作指令,管理行为向公司CEO负责； 2、负责本部门的员工队伍组建,提出对下属人员的调配,培训,考核意见； 3、制定本部门的业务内容、范围、及推进战略。 | E15: 吕振国 | F15: 上海
A16: 运营中心 | B16: 总经理 | C16: 1 | D16: 1、以企业降本或提效为最终目标，进行企业信息化长远规划和建设； 2、统筹集团的信息化系统供应商开发，产品选型，与相关业务部门负责人共同评选出选最适合的产品或供应商； 3、对接公司业务部门，了解业务部门的信息化诉求，以业务部门为中心，进行信息化建设或优化； 4、企业信息化项目实施过长中，对业务需求、系统方案进行把关，对项目质量和进度进行风险管控和监督； 5、负责运营系统部团队人才梯队搭建与培养，管理和激励等工作，对管对进行有效的管理、提升和考评。 | E16: 吕振国 | F16: 上海
B17: 资材管理部 | C17: 6 | D17: 1、参与制定公司战略与年度经营计划，协同采购活动整体优化； 2、建立健全采购流程、供应商绩效管理流程，进行有效规划及优化，规范供应商管理； 3、负责集团供应商符合性审查，组织供应商的整体评估，根据事业部； 4、搭建采购体系管理团队，通过有效的培训、激励和绩效管理，提升组织能力； 5、建立完善的采购管理数据和指标监控体系； 6、发起、统筹采购管理系统建设和持续改进。 7、负责公司信息管理系统的建立及信息资源的配置； 8、负责团队人力资源的开发、管理和提高； 9、负责资材中心组织结构的调整； 10、负责组织完成集团下达的其它临时性、阶段性工作和任务。 11.根据海外各国关务政策制定我司关务工作制度操作流程 12.收集整理各国贸易管制措施，制定我司符合本地报关策略和实施方案，并根据海外各国优惠税率政策优化我司本地报关方式，并指导清关工作； 13.对关务人员进行政策和专业知识培训，为直接领导提供关务决策依据，并为领导决策提供专业参谋； 14.负责建立和维护与海关、商检、外经局等政府部门之间的工作关系，并随时了解最新政策资讯，将对公司有影响的方针，政策及时通告相关部门和人员，确保公司进出口流程始终保持在符合国家法律，法规的范围内，保持物流链处于流畅状态； 15.负责对报关课进行综合事务性管理，包括（但不限于）报关员工作监督制度的建立、业绩考核、内部培训等日常人员管理工作。 | E17: 赵华夏 | F17: 上海
B18: 人力资源部 | C18: 6 | D18: 1、根据公司战略及业务发展规划，制定人力资源战略规划与行政战略规划，全面统筹规划本中心工作； 2、根据公司战略制定人力资源规划方案，并组织实施人力资源体系的年度计划 3、制定、推动、监督人力资源各项流程和制度，并根据公司发展情况不断修订 4、协调、指导各部门在人力资源管理方面等工作的开展，确保公司人力资源的合理使用，及时处理公司管理过程中的重大人力资源问题 5、负责绩效考核体系管理，制定和修订公司绩效考核制度，根据公司绩效考核原则结合各部门业务发展需求，设计、修订与业务相匹配的绩效考核要求方案；对各部门绩效评价过程中进行监督控制，及时解决其中出现的问题；6、对本中心管理中出现的问题，提出改进建议和实施方案，经批准后组织实施；监督、检查所辖中心的各项工作及计划的执行情况，本中心员工的培训、考核工作。 7、审核公司年度人力资源预算方案,行政费用预算； 8、负责建立公司内部畅通的沟通渠道，及时了解员工意见和想法。积极听取和采纳员工合理化建议，并反馈给相关部门。受理员工投诉，调查后落实相关部门解决。 9、规范完善公司人力资源管理系统，提供各项人事工作支持。 11、负责公司整体的文化建设工作 12、及时解决公司管理过程中的重大劳资纠纷及人力资源问题。 13、组织公司内外部重要会议，负责对政府机关及其他外部组织机构的联络、接待工作； 14、统筹维护并保证本部门管理体系（ISO9001/ISO14001）正常、有效的运行； 15、统筹识别本部门的风险和机遇，并定期参与评审及执行相应的管理措施以规避或者降低风险级别； 16、解本部门的环境因素、重要环境因素清单，制定本部门重要环境因素的管理方法； 17、完成上级领导委派的其他工作事项。
B19: 行政管理部 | C19: 10 | D19: 1、根据公司发展规划，组织制定行政部工作发展规划，并且全面负责本部门的工作； 2、负责统筹各项行政管理制度的制定、完善、宣导、执行与监督，使公司的管理工作规范化； 3、规范完善公司行政管理工作，提供各项行政后勤支持； 4、组织公司内外部重要会议，负责对政府机关及其他外部组织机构的联络、接待工作； 5、统筹维护并保证本部门管理体系（ISO9001/ISO14001）正常、有效的运行； 6、统筹识别本部门的风险和机遇，并定期参与评审及执行相应的管理措施以规避或者降低风险级别； 7、了解本部门的环境因素、重要环境因素清单，制定本部门重要环境因素的管理方法； 8、完成上级领导委派的其他工作事项。
B20: 制造部 | C20: 68 | D20: 1、负责制定并监督生产计划、工作计划和培训计划的实施； 2、负责现有设备生产负荷统计及产销平衡调度，保证设备在受控状态下运行，合理配置生产资源组织生产计划的安全实施； 3、负责生产进度控制，产品质量控制，生产成本控制以及对库存与资金占用控制； 4、负责生产环境卫生改善及推行6S管理； 5、负责本部门工作流程和产品质量的持续改进和完善； 6、负责本部门与公司其它部门之间的协调工作； 7、负责本部门人员管理、团队建设、绩效辅导； 8、按照公司EPROS流程规定进行业务管理； 9、其他上级领导安排事宜。
B21: 品质管理部 | C21: 10 | D21: 1、调节处理重大质量纠纷 2、监督与评价工厂质量情况，推进工厂质量系统改善 3、识别与评价本部门风险和机遇，并制定相应的对策 4、建立和完善品质管理系统，包括产品标准、过程标准、持续改进等 5、根据国际、国家、行业动态，制定/优化企业标准 6、每年各部门相互之间交叉审核，发现存在的问题和不足 7、定期与关键客户沟通交流，掌握产品质量状况，挖掘客户关键的新质量要求 8、识别与评价本部门的环境因素；参与制定重要环境因素的管理方法； 9、熟悉管理方针和目标；维护、推动本部门管理体系的有效运行； 10、上级领导交代的其他事项。
B22: 设备开发部 | C22: 5 | D22: 上海总部&山东工厂&越南工厂 1、根据公司的发展规划，负责公司的设备开发管理工作； 2、根据公司发展需要，负责制定公司年度的设备开发工作计划和季度计划以及开发策略； 3、负责公司设备管理体系的搭建与优化工作；负责完善与优化部门制度、流程的审批； 4、负责承接各事业部产品配套设备的开发管理工作； 5、负责持续提升公司现有生产设备生产效率，节约成本； 6、负责根据公司产品的描述和工艺，规划现有生产线的设备方案与需求，完善生产的设备需求； 7、负责优化与完善公司现有设备，改进和保障运行设备方案，提升产品质量的稳定； 8、负责设备开发队伍的组建与管理，指导其完成公司计划与设备开发任务； 9、负责定期召开会议，组织团队年度、月度等工作计划，推进团队正常有序的达成工作任务； 10、负责培养储备设备管理人员，并做好梯队建设； 11、负责组织设备团队相关人员集中学习培训，提高与业技能和组织管理能力； 12、负责与部门之间的沟通协调以及相关外部关系的建立工作： 13、负责自研设备总体规划： 14、负责自研设备上位机与下位机软件开发； 15、负责外购设备技术协议审批、出厂验收； 16、统筹维护并保证本部门管理体系（ISO9001/ISO14001）正常、有效的运行，并对所属人员进行宣导； 17、统筹识别本部门的风险和机遇，并定期参与评审及执行相应的管理措施以规避或者降低风险级别； 18、了解本部门的环境因素、重要环境因素清单，制定本部门重要环境因素的管理方法； 19、上级安排的其它工作。
B23: 认证服务部 | C23: 4 | D23: 1、负责领导本部门的日常管理工作； 2、制定，实施、完成部门绩效指标任务工作； 3、统筹部门的规划与发展工作； 4、对内检测认证的开发、承接，跟进维护等工作； 5、规划检测认证潜在的客户与市场方向； 6、开发检测认证的新合作渠道，新市场； 7、参与各类锂电池标准的参与制定工作； 8、行业内的市场分析，行情的收集整理，总结工作； 9、部门内运营能力的月报、年报分析，总结、汇报； 10、协助公司其它部门的检测认证需求工作； 11、统筹维护并保证本部门管理体系（ISO9001/ISO14001）正常、有效的运行，并对所属人员进行宣导； 12、统筹识别本部门的风险和机遇，并定期参与评审及执行相应的管理措施以规避或者降低风险级别； 13、了解本部门的环境因素、重要环境因素清单，制定本部门重要环境因素的管理方法； 14、完成上级领导交待的各项临时事务。
B24: 体系管理部 | C24: 2 | D24: 1、负责组织编制，完善相关体系文件和制度文件； 2、负责组织公司安全检查、隐患排查及监督整改事项的落实和申报工作。 3、负责员工安全教育，开展安全活动，参与安全事故的调查和处理。 4、负责二方、三方的例行检查和稽核，检查问题点的整改； 5、对员工健康进行监控，及时组织员工进行职业健康体检，维护职业卫生员工档案； 6、公司EHS相关许可证（如排污许可证）申请、年审、变更； 7、公司危险源及环境因素识别与管控，提出改善方案； 8、负责临时用电、动火等特殊作业的审批工作，对作业条件把关，并建立台账； 9、负责消防演练、化学品泄露等相关演习，制作完整演练PPT报告； 10、负责稽查安全工作的落实情况，组织安全会议； 11、新建项目安全、环保、职业卫生三同时的实施。
B25: 系统开发部 | C25: 10 | D25: 1、以企业降本或提效为最终目标，进行企业信息化长远规划和建设； 2、统筹集团的信息化系统供应商开发，产品选型，与相关业务部门负责人共同评选出选最适合的产品或供应商； 3、对接公司业务部门，了解业务部门的信息化诉求，以业务部门为中心，进行信息化建设或优化； 4、企业信息化项目实施过长中，对业务需求、系统方案进行把关，对项目质量和进度进行风险管控和监督，； 5、负责应用系统团队人才梯队搭建与培养，管理和激励等工作，对管对进行有效的管理、提升和考评。
A26: 研发中心 | C26: 2 | D26: 1、参与制定公司发展战略、年度经营计划和预算方案； 2、组织研究行业最新产品的技术发展方向，主持制定技术发展战略规划； 3、管理公司的整体核心技术，组织制定和实施重大技术决策和技术方案； 4、及时了解和监督技术发展战略规划的执行情况； 5、领导分管部门制度并组织实施年度工作计划，完成年度任务目标； 6、主持新产品项目所需的物料开发、试产、改进以及产线布局等工作； 7、研究决策事业部技术发展路线，规划开发事业部产品； 8、指导、审核项目总体技术方案，对各项目进行最后的质量评估； 9、与客户进行技术交流，了解客户在技术与业务上的发展要求，并解答客户提出的与产品技术相关的问题。 10、制定技术人员的培训计划，并组织安排事业部其他相关人员的技术培训。 | E26: 吕振国 | F26: 上海
A27: 董事会 | C27: 0 | D27: 1、参与内部事务及提供法律保障 （1）参与公司的投资并购、产权转让、招投标及重组等重大经济活动的决策，并处理有关法律事务； （2）向公司业务部门、下属公司提供有关法律咨询； （3）为各部门提供法律咨询，确保各项流程符合法律法规。 2、完善法律风险管理 （1）及时完成合同起草或审核，防范风险、维护公司利益、规范管理； （2）加强员工法律意思的培养，严格遵守相关法律和各项规章制度； （3）做好公司各类案件的诉讼和应诉工作，降低公司因仲裁、诉讼而产生的损失； （4）加强公司内部法律事务管理人员培养，结合本公司的特点和实际情况建立适合的法律风险防范体系； （5）配合业务和财务做好应收账款的催收工作； （6）知识产权管理工作，培养/招聘专门的知识产权管理人员，负责知识产权工作的开展； 3、外联工作 代表公司联络公检法机关和律师事务所，与相关部门建立良好关系； 4、部门建设及团队建设 （1）搭建法务部管理体系，编制法务部相关管理制度，保证法务部顺畅嵌入公司业务流程； （2）做好本部门员工的培训与考核工作，对部属进行日常的业务辅导； （3）负责本部门人员的培训，不断提升团队专业水平，完成公司的各项法律工作； 5、政府项目申报工作 6、领导交办的其他工作。 | E27: 吕振国 | F27: 上海
A29: 请确认截至2023年12月31日公司的股权架构情况如下图所示：

Sheet 2 关联公司信息
A1: ='1 组织结构及管理架构'!A1 -> 上海派智能源股份有限公司
A3: 附件二：关联方相关信息
A4: 以下内容根据贵公司2022年度资料清单中提供的相关信息预填，请贵公司就2023年度情况对以下描述进行确认或更新。
A5: 请贵公司提供截至2023年12月31日的关联公司信息。
A6: 行次 | B6: 关联方名称 | C6: 法定代表人 | D6: 与本公司关系 | E6: 注册地址 | F6: 经营地址
B7: 1 | C7: 2 | D7: 3 | E7: 4 | F7: 5
A8: 1 | B8: 山东派智电子有限公司 | C8: 王宏义 | D8: 控股 | E8: 山东省济宁市微山县经济开发区东风东路36号高新技术产业园2号楼 | F8: 山东省济宁市微山县经济开发区东风东路36号高新技术产业园2号楼
A9: 2 | B9: 山东派智新能源科技有限公司 | C9: 高朋坤 | D9: 控股 | E9: 山东省济宁市微山县经济开发区东风东路36号高新技术产业园1号楼 | F9: 山东省济宁市微山县经济开发区东风东路36号高新技术产业园1号楼
A10: 3 | B10: 上海能勤网络科技有限公司 | C10: 刘博赫 | D10: 控股 | E10: 上海市奉贤区金钱公路3329号4幢 | F10: 上海市奉贤区金钱公路3329号4幢
A11: 4 | B11: PYTES (VIET NAM) ENERGY CO.,LTD | C11: LYU, ZHENGUO | D11: 控股 | E11: Lô G3-1 đường D3, KCN Việt Hóa - Đức Hòa III, Xã Đức Lập Hạ, Huyện Đức Hoà, Tỉnh Long An, Việt Nam | F11: Lô G3-1 đường D3, KCN Việt Hóa - Đức Hòa III, Xã Đức Lập Hạ, Huyện Đức Hoà, Tỉnh Long An, Việt Nam
A12: 5 | B12: PYTES B.V. | C12: Sun, Shengwei Chang, Yanjie | D12: 控股 | E12: Molendijk-Zuid 23 B, 5482WZ Schijndel | F12: Molendijk-Zuid 23 B, 5482WZ Schijndel
A13: 6 | B13: PYTES (HongKong) ENERGY LIMITED | C13: LYU, ZHENGUO | D13: 控股 | E13: 金鐘金鐘道89號力寶中心第一座10樓1003室, 香港 | F13: 金鐘金鐘道89號力寶中心第一座10樓1003室, 香港
A14: 7 | B14: PYTES (USA) Energy,Inc | C14: LYU, ZHENGUO | D14: 控股 | E14: UNITS 107, 920 S HOLGATE, SEATTLE, WA, 98134, UNITED STATES | F14: UNITS 107, 920 S HOLGATE, SEATTLE, WA, 98134, UNITED STATES
A15: 8 | B15: PYTES (SINGAPORE) ENERGY PTE. LTD. | C15: LYU, ZHENGUO MAO,HONG | D15: 控股 | E15: 04, 17 CLIFFORD CENTRE, 24, RAFFLES PLACE 048621 | F15: 04, 17 CLIFFORD CENTRE, 24, RAFFLES PLACE 048621
A16: 9 | B16: PYTES Hungary Korlátolt Felelősségű Társaság | C16: Shengwei Sun | D16: 控股 | E16: 1053 Budapest, Károlyi utca 12. 2. em. | F16: 1053 Budapest, Károlyi utca 12. 2. em.
A17: 10 | B17: PYTES GmbH | C17: Shengwei Sun | D17: 控股 | E17: Kleinkoschener Dorfstraße 6, 01968 Senftenberg, Deutschland | F17: Kleinkoschener Dorfstraße 6, 01968 Senftenberg, Deutschland
A18: 11 | B18: PYTES Energy Inc. | C18: DAN WANG | D18: 控股 | E18: 6721 TILLAMOOK AVE, WESTMINSTER CA 92683 | F18: 6721 TILLAMOOK AVE, WESTMINSTER CA 92683

Sheet 关联方个人信息
A1: 个人关联方 | B1: 国籍 | C1: 关联关系类型 | D1: 居住地址
A2: 没找到

Sheet 关联关系变化情况
A1: 关联方名称 | B1: 国家/地区 | C1: 关联关系类型 | D1: 起止日期 | E1: 变化原因
A2: 山东派智电子有限公司 | B2: 中华人民共和国 | C2: 控股关联 | D2: 2023年1月1日 -2023年12月31日
A3: 山东派智新能源科技有限公司 | B3: 中华人民共和国 | C3: 控股关联 | D3: 2023年1月1日 -2023年12月31日
A4: 上海能勤网络科技有限公司 | B4: 中华人民共和国 | C4: 控股关联 | D4: 2023年1月1日 -2023年12月31日
A5: PYTES (VIET NAM) ENERGY CO.,LTD | B5: 越南社会主义共和国 | C5: 控股关联 | D5: 2023年1月1日 -2023年12月31日
A6: PYTES B.V. | B6: 荷兰王国 | C6: 控股关联 | D6: 2023年1月1日 -2023年12月31日
A7: PYTES (HongKong) ENERGY LIMITED | B7: 中国香港特别行政区 | C7: 控股关联 | D7: 2023年1月1日 -2023年12月31日
A8: PYTES (USA) Energy,Inc | B8: 美利坚合众国 | C8: 控股关联 | D8: 2023年1月1日 -2023年12月31日
A9: PYTES (SINGAPORE) ENERGY PTE. LTD. | B9: 新加坡共和国 | C9: 控股关联 | D9: 2023年1月1日 -2023年12月31日
A10: PYTES Hungary Korlátolt Felelősségű Társaság | B10: 匈牙利共和国 | C10: 控股关联 | D10: 2023年1月1日 -2023年12月31日
A11: PYTES GmbH | B11: 德意志联邦共和国 | C11: 控股关联 | D11: 2023年1月1日 -2023年12月31日
A12: PYTES Energy Inc. | B12: 美利坚合众国 | C12: 控股关联 | D12: 2023年1月1日 -2023年12月31日

Sheet 3 分部财务数据
A1: ='1 组织结构及管理架构'!A1 -> 上海派智能源股份有限公司
A3: 附件三：分部财务数据
A5: 请贵公司拆分截至2023年12月31日的财务数据。如果没有相关的数据，请标明“N/A”。
A6: 项目 | B6: 备注 | C6: 销售业务 | G6: 其他业务（如有） | K6: 合计
C7: 境外 | E7: 境内 | G7: 境外 | I7: 境内
C8: 关联方 | D8: 非关联方 | E8: 关联方 | F8: 非关联方 | G8: 关联方 | H8: 非关联方 | I8: 关联方 | J8: 非关联方
A10: 一、营业收入 | C10: 1.7412012e+08 | D10: 1.8241153e+08 | E10: 1.5437723e+08 | F10: 1.7024812e+08 | J10: 2.6703791e+08 | K10: =C10+D10+E10+F10+J10 -> 9.4819492e+08
A11: 其中：主营业务收入 | C11: 1.7412012e+08 | D11: 1.8241153e+08 | E11: 1.5437723e+08 | F11: 1.7024812e+08 | J11: 2.6703791e+08 | K11: =C11+D11+E11+F11+J11 -> 9.4819492e+08
A12: 减：营业成本 | C12: 1.1580386e+08 | D12: 1.3900979e+08 | E12: 1.4974591e+08 | F12: 1.3737937e+08 | J12: 2.6280504e+08 | K12: =C12+D12+E12+F12+J12 -> 8.0474397e+08
A13: 其中：主营业务成本 | C13: 1.1580386e+08 | D13: 1.3900979e+08 | E13: 1.4974591e+08 | F13: 1.3737937e+08 | J13: 2.6280504e+08 | K13: =C13+D13+E13+F13+J13 -> 8.0474397e+08
A14: 营业税金及附加 | C14: 470622.63 | D14: 564930.67 | E14: 608561.88 | F14: 558304.71 | J14: 1068030 | K14: =C14+D14+E14+F14+J14 -> 3270449.9
A15: 其中：主营业务税金及附加
A16: 销售费用 | C16: 7957554 | D16: 9552167.8 | E16: 10289909 | F16: 9440132.4 | J16: 18058857 | K16: =C16+D16+E16+F16+J16 -> 55298621
A17: 管理费用 | C17: 12326204 | D17: 14796252 | E17: 15939009 | F17: 14622710 | J17: 27973064 | K17: =C17+D17+E17+F17+J17 -> 85657238
A18: 财务费用 | C18: -71102.076 | D18: -85350.216 | E18: -91942.059 | F18: -84349.16 | J18: -161358.91 | K18: =C18+D18+E18+F18+J18 -> -494102.42
A19: 资产减值损失 | C19: 86617.187 | D19: 103974.4 | E19: 112004.64 | F19: 102754.9 | J19: 196568.87 | K19: =C19+D19+E19+F19+J19 -> 601920
A20: 加：公允价值变动收益（损失以“-”号填列）
A21: 投资收益（损失以“-”号填列） | C21: 119313.02 | D21: 143222.15 | E21: 154283.61 | F21: 141542.33 | J21: 270768.73 | K21: =C21+D21+E21+F21+J21 -> 829129.84
A22: 其中：对联营企业和合营企业的投资收益
A23: 二、营业利润（亏损以“-”号填列）＝ | C23: =C10-C12-C14-C16-C17-C18+C19+C21 -> 37838916 | D23: =D10-D12-D14-D16-D17-D18+D19+D21 -> 18820937 | E23: =E10-E12-E14-E16-E17-E18+E19+E21 -> -21847933 | F23: =F10-F12-F14-F16-F17-F18+F19+F21 -> 8576254.7 | J23: =J10-J12-J14-J16-J17-J18+J19+J21 -> -42238384 | K23: =C23+D23+E23+F23+J23 -> 1149791.7 | L23: =K10-K12-K14-K16-K17 -> -775360.57
A27: 说明：分别披露关联交易和非关联交易的收入、成本、费用和利润，不能直接归集的，按照合理比例划分，并说明该划分比例的依据。

Sheet 关联交易汇总表
A1: 关联交易类型 | B1: 境外交易金额 | C1: 境内交易金额 | D1: 交易总额
B2: A | C2: B | D2: C=A+B
A3: 关联采购 | B3: 0 | C3: 3.7784013e+08 | D3: =B3+C3 -> 3.7784013e+08
A4: 关联销售 | B4: 1.7532131e+08 | C4: 1.5826426e+08 | D4: =B4+C4 -> 3.3358557e+08
A5: 合计 | B5: =SUM(B3:B4) -> 1.7532131e+08 | C5: =SUM(C3:C4) -> 5.3610438e+08 | D5: =SUM(D3:D4) -> 7.1142569e+08

Sheet 4 供应商清单
A1: ='1 组织结构及管理架构'!A1 -> 上海派智能源股份有限公司
A3: 附件四： 供应商清单
A5: 请贵公司提供截至2023年12月31日包括关联方在内的贵公司的主要供应商详情。 请注明供应商位于境内还是境外、采购的产品类型、采购金额及每个供应商的采购金额占贵公司采购总金额的比例等。
A6: 项目 | B6: 编号 | C6: 供应商名称 | D6: 产品类型（例如原材料，半成品或成品） | E6: 会计年度2023 | H6: 运输条款（例如FOB，CIF等） | I6: 支付货币 （例如美元） | J6: 支付条款（例如发票开具日期30天内）
E7: 金额 （人民币） | F7: 占采购总金额比例 | G7: 占关联采购总金额比例
A8: 关联供应商
A9: 境外关联采购 | B9: 1
B10: 2
B11: 3
B12: 4
B13: 5
B14: 其他
B15: 境外关联采购小计
A16: 境内关联采购 | B16: 1 | C16: 山东电子 | E16: 3.2317118e+08 | F16: =E16/$E$40 -> 0.41284863 | G16: =E16/E22 -> 0.85406295 | J16: 90
B17: 2 | C17: 山东新能源 | E17: 55221512 | F17: =E17/$E$40 -> 0.070545045 | G17: =E17/E22 -> 0.14593705 | J17: 60
B18: 3
B19: 4
B20: 5
B21: 其他
B22: 境内关联采购小计 | E22: =SUM(E16:E21) -> 3.7839269e+08
A23: 关联采购小计 | E23: =E15+E22 -> 3.7839269e+08
A24: 非关联供应商
A25: 境外非关联采购 | B25: 1 | C25: LG Energy Solution, LTD. | D25: 原材料 | E25: 810108 | F25: =E25/$E$40 -> 0.0010349066 | J25: 款到发货
B26: 2 | C26: YUAN WEN SHING INDUSTRIES CORP | D26: 原材料 | E26: 2857.36 | F26: =E26/$E$40 -> 3.6502549e-06 | J26: 款到发货
B27: 3 | C27: 迈特国际有限公司 | D27: 原材料 | E27: 118854.21 | F27: =E27/$E$40 -> 0.00015183532 | J27: 预付50%，尾款50%货到票到月结90天
B28: 4 | C28: TOYOMURA ELECTRONICS(HK) CO.,LTD | D28: 原材料 | E28: 223706.7 | F28: =E28/$E$40 -> 0.00028578354 | J28: 预付30%，余款发货前付清
B29: 5 | C29: Quick Circuit | D29: 原材料 | E29: 393734.15 | F29: =E29/$E$40 -> 0.00050299227 | J29: 款到发货
B30: 其他
B31: 境外非关联采购小计 | E31: =SUM(E25:E30) -> 1549260.4
A32: 境内非关联采购 | B32: 1 | C32: 松下电器机电（中国）有限公司(RMB) | D32: 原材料 | E32: 96577703 | F32: =E32/$E$40 -> 0.12337725 | J32: 货到票到合格验收后月结30天
B33: 2 | C33: 爱尔集新能源（南京）有限公司 | D33: 原材料 | E33: 78659891 | F33: =E33/$E$40 -> 0.10048739 | J33: 货到票到合格验收后月结90天
B34: 3 | C34: 瑞浦兰钧能源股份有限公司 | D34: 原材料 | E34: 78218501 | F34: =E34/$E$40 -> 0.099923518 | J34: 货到票到合格验收后月结45天
B35: 4 | C35: 友尚电子 (上海)有限公司 | D35: 原材料 | E35: 38067581 | F35: =E35/$E$40 -> 0.048631035 | J35: 货到票到合格验收后月结90天
B36: 5 | C36: 中银（宁波）电池有限公司 | D36: 原材料 | E36: 20767406 | F36: =E36/$E$40 -> 0.026530198 | J36: 发货30天付款
B37: 其他 | E37: =E39-E31-E32-E33-E34-E35-E36 -> 90550664 | F37: =E37/$E$40 -> 0.11567776
B38: 境内非关联采购小计 | E38: =SUM(E32:E37) -> 4.0284175e+08
A39: 非关联采购小计 | E39: =E40-E23 -> 4.0439101e+08
A40: 合计 | E40: 7.827837e+08

Sheet 5 客户清单
A1: ='1 组织结构及管理架构'!A1 -> 上海派智能源股份有限公司
A3: 附件五：客户清单
A5: 请贵公司提供截至【年度】年12月31日包括关联方在内的贵公司的主要客户详情。 请注明客户位于境内还是境外、相关的产品类型、销售收入及每个客户的销售收入占贵公司销售总收入的比例等。
A6: 项目 | B6: 编号 | C6: 客户名称 | D6: 产品以及产品细分（例如A1，B2等） | E6: 会计年度【年度】 | H6: 运输条款（例如FOB，CIF等） | I6: 支付货币 （例如美元） | J6: 支付条款（例如发票开具日期30天内）
E7: 金额 （人民币） | F7: 占销售总收入比例 | G7: 占关联销售总收入比例
A8: 关联客户
A9: 境外关联销售 | B9: 1 | C9: PYTES (VIET NAM) ENERGY CO.，LTD | D9: 电子设备 | E9: 1167267
B10: 2 | C10: PYTES B.V. | D10: 其他，其他，电子设备 | E10: 26143529
B11: 3 | C11: PYTES (SINGAPORE) ENERGY PTE. LTD. | D11: 其他，其他 | E11: 1.2698141e+08
B12: 4 | C12: PYTES (USA) Energy，Inc | D12: 其他，其他 | E12: 21029104
B13: 5
B14: 其他
B15: 境外关联销售小计 | E15: =SUBTOTAL(9,E9:E14) -> 1.7532131e+08 | F15: =IFERROR(E15/E$40,0) -> 0.24616551 | G15: =IFERROR(E15/E$23,0) -> 0.52556624
A16: 境内关联销售 | B16: 1 | C16: 山东派智电子有限公司 | D16: 其他,其他,机械机器设备,器具工具家具,电子设备 | E16: 1.4733931e+08
B17: 2 | C17: 山东派智新能源科技有限公司 | D17: 其他,其他,电子设备 | E17: 10924944
B18: 3
B19: 4
B20: 5
B21: 其他
B22: 境内关联销售小计 | E22: =SUBTOTAL(9,E16:E21) -> 1.5826426e+08 | F22: =IFERROR(E22/E$40,0) -> 0.22221601 | G22: =IFERROR(E22/E$23,0) -> 0.47443376
A23: 关联销售小计 | E23: =SUBTOTAL(9,E9:E22) -> 3.3358557e+08 | F23: =IFERROR(E23/E$40,0) -> 0.46838152 | G23: =IFERROR(E23/E$23,0) -> 1
A24: 非关联客户
A25: 境外非关联销售 | B25: 1
B26: 2
B27: 3
B28: 4
B29: 5
B30: 其他
B31: 境外非关联销售小计 | E31: =SUBTOTAL(9,E25:E30) -> 0 | F31: =IFERROR(E31/E$40,0) -> 0 | G31: =IFERROR(E31/E$39,0) -> 0
A32: 境内非关联销售 | B32: 1 | C32: 山东派智电子有限公司 | D32: 其他,其他,机械机器设备,电子设备 | E32: 3.2333397e+08
B33: 2 | C33: 山东派智新能源科技有限公司 | D33: 其他，其他 | E33: 55221512
B34: 3 | C34: 上海能勤网络科技有限公司 | D34: 其他 | E34: 68026
B35: 4
B36: 5
B37: 其他
B38: 境内非关联销售小计 | E38: =SUBTOTAL(9,E32:E37) -> 3.7862351e+08 | F38: =IFERROR(E38/E$40,0) -> 0.53161848 | G38: =IFERROR(E38/E$39,0) -> 1
A39: 非关联销售小计 | E39: =SUBTOTAL(9,E25:E38) -> 3.7862351e+08 | F39: =IFERROR(E39/E$40,0) -> 0.53161848 | G39: =IFERROR(E39/E$39,0) -> 1
A40: 合计 | E40: =SUM(E23,E39) -> 7.1220907e+08 | F40: =IFERROR(E40/E$40,0) -> 1

Sheet 6 劳务交易表
A3: 附件六：劳务交易表
A5: 请贵公司提供截至2023年12月31日贵公司的关联劳务交易详情。
A6: 行次 | B6: 关联交易类型 | C6: 关联方名称 | D6: 关联交易内容 | E6: 交易金额 | F6: 比例 | G6: 占总劳务收入比重（%）
B8: 1 | C8: 2 | D8: 3 | E8: 4 | F8: 5 | G8: 6
A9: 1 | B9: 境外关联 劳务收入
A10: 2
A11: 3
A12: 4
A13: 5
A14: 6 | B14: ──── | C14: 其他关联方 | D14: ────
A15: 7 | B15: 境外关联劳务收入小计 | E15: =ROUND(SUM(E9:E14),2) -> 0
A16: 8 | B16: 境内关联 劳务收入
A17: 9
A18: 10
A19: 11
A20: 12
A21: 13 | B21: ──── | C21: 其他关联方 | D21: ────
A22: 14 | B22: 境内关联劳务收入小计 | E22: =ROUND(SUM(E16:E21),2) -> 0
A23: 15 | B23: 境内外关联和非关联劳务收入合计
A24: 16 | B24: 境外关联 劳务支出
A25: 17
A26: 18
A27: 19
A28: 20
A29: 21 | B29: ──── | C29: 其他关联方 | D29: ────
A30: 22 | B30: 境外关联劳务支出小计 | E30: =ROUND(SUM(E24:E29),2) -> 0
A31: 23 | B31: 境内关联 劳务支出
A32: 24
A33: 25
A34: 26
A35: 27
A36: 28 | B36: ──── | C36: 其他关联方 | D36: ────
A37: 29 | B37: 境内关联劳务支出小计 | E37: =ROUND(SUM(E31:E36),2) -> 0
A38: 30 | B38: 境内外关联和非关联劳务支出合计

Sheet 劳务成本归集
A1: 劳务内容 | B1: 分配方法 | C1: 总成本费用 | D1: 【清单模板-数据表B5】
D2: 所需承担的比例
A3: 市场营销服务 | B3: 销售额 | C3: XX,XXX | D3: XX%
A4: 行政支持服务 | B4: 销售额 | C4: XX,XXX | D4: XX%
A5: 信息技术服务 | B5: 人数 | C5: XX,XXX | D5: XX%
A6: 没找到

Sheet 资金融通
A1: 关联方 | B1: 金额
A4: 合计
A5: 没找到

Sheet 公司间资金融通交易总结
A1: 缔约方 | B1: 公司间资金融通交易性质 | C1: 货币 | D1: 本金 | E1: 本金 | F1: 到期期限 | G1: 利率 | H1: 利息收入/利息支出 | I1: 利息收入/利息支出
D2: （原币） | E2: （人民币） | H2: （原币） | I2: （人民币）
B3: 借款/贷款
A4: 没找到

Sheet 有形资产信息
A1: 资产净值 | B1: 年初数 | C1: 年末数
A2: 房屋及建筑物
A3: 电脑设备
A4: 机器设备
A5: 办公设备
A6: 家具
A7: 运输设备
A8: 生产设备
A9: 其他
A10: 合计
B11: 无列示

Sheet 功能风险汇总表
A1: 序号 | B1: 风险 | C1: 【清单模板-数据表B5】 | D1: 关联方
A2: 1
A3: 2
A4: 3
B5: 没找到

Sheet PL
A2: 项目 | B2: 公式 | C2: 【年度】
C3: 2023
A4: 营业收入 | B4: a | C4: 9.4819492e+08
A5: 减：营业成本 | B5: b | C5: 8.0474397e+08
A6: 税金及附加 | B6: c | C6: 3270449.9
A7: 营业利润 | B7: d = a-b-c | C7: =C4-C5-C6 -> 1.401805e+08
A8: 减：销售费用 | B8: e | C8: 55298621
A9: 管理费用 | B9: f | C9: 85657238
A10: 资产减值损失 | B10: g | C10: -1388027.2
A11: 息税前利润 | B11: h = a-b-c-e-f-g | C11: =C4-C5-C6-C8-C9-C10 -> 612666.61
A12: 营业成本及费用 | B12: i = b+c+e+f+g | C12: =C5+C6+C8+C9+C10 -> 9.4758225e+08
A13: 完全成本加成率 | B13: j= h/i | C13: =C11/C12 -> 0.00064655771
A17: 根据访谈，关联销售以审计报告为准
A19: 境外关联销售 | B19: 1
B20: 2
B21: 3
B22: 4
B23: 5
B24: 其他
B25: 境外关联销售小计 | E25: =SUBTOTAL(9,E19:E24) -> 0
A26: 境内关联销售 | B26: 1
B27: 2
B28: 3
B29: 4
B30: 5
B31: 其他
B32: 境内关联销售小计 | E32: =SUBTOTAL(9,E26:E31) -> 0
A48: 关联交易类型 | B48: 境外交易金额 | C48: 境内交易金额 | D48: 交易总额
B49: A | C49: B | D49: C=A+B
A50: 关联采购
A51: 关联销售
A52: 总计 | B52: =SUM(B50:B51) -> 0
A57: 关联方名称 | C57: 交易金额 | D57: 占采购、销售总额比例(%)
A58: 关联
A59: 采购
A60: 关联采购总计
A61: 关联
A62: 销售
A64: 关联销售总计

Sheet PL含特殊因素调整
B2: 项目 | C2: 公式 | D2: 2023 (销售业务) 报告版本 | E2: 2023 (汇缴利润表) | F2: 营业成本特调 (工、费) | G2: 调整后2023年 | H2: 2022 (汇缴利润表) | I2: 变动率 | K2: 其他业务 | L2: 合计
B3: 营业收入 | C3: [A] | D3: 6.81157e+08 | E3: 9.4819492e+08 | G3: 9.4819492e+08 | H3: 1.4203065e+09 | I3: -0.33240122 | K3: 2.6703791e+08 | L3: 9.4819492e+08
B4: 营业成本 | C4: [B] | D4: 5.4193893e+08 | E4: 8.0474397e+08 | F4: -3866383 | G4: 8.0087759e+08 | H4: 1.2500107e+09 | I4: -0.35621034 | K4: 2.6280504e+08 | L4: 8.0474397e+08
B5: 其中：原材料 | E5: 7.6455848e+08 | F5: 0 | G5: 7.6455848e+08 | K5: 0
B6: 人工 | E6: 18525474 | F6: -1845074.3 | G6: 16680400 | K6: 0
B7: 费用 | E7: 21660017 | F7: -2021308.7 | G7: 19638708 | K7: 0
B8: 营业税金及附加 | C8: [C] | D8: 2349400.8 | E8: 3270449.9 | G8: 3270449.9 | H8: 1447219.4 | I8: 1.2598163 | K8: 921049.16 | L8: 3270449.9
B9: 销售费用 | C9: [D] | D9: 39725000 | E9: 55298621 | F9: -1973252 | G9: 53325369 | H9: 57609078 | I9: -0.040105784 | K9: 15573621 | L9: 55298621
B10: 管理费用 | C10: [E] | D10: 73651558 | E10: 85657238 | F10: -18084655 | G10: 67572583 | H10: 1.0198946e+08 | I10: -0.16013637 | K10: 12005680 | L10: 85657238
B11: 资产损失 | C11: [F] | D11: -997120.34 | E11: -1388027.2 | G11: -1388027.2 | H11: 0 | K11: -390906.85 | L11: -1388027.2
B12: 总成本 | C12: [G]=[B]+[C]+[D]+[E]+[F] | D12: 6.5666776e+08 | E12: 9.4758225e+08 | F12: -21951038 | G12: 9.2365796e+08 | H12: 1.4110565e+09 | I12: -0.32845902 | K12: 2.9091449e+08 | L12: 9.4758225e+08
B13: 息税前利润 | C13: [H]=[A]-[G] | D13: 24489240 | E13: 612666.61 | G13: 24536956 | H13: 9250065.7 | I13: -0.93376624 | K13: -23876573 | L13: 612666.62
B14: 息税前利润率 | C14: [I]=[H]/[A] | D14: 0.035952416 | E14: 0.00064613994 | G14: 0.025877545 | H14: 0.0065127249 | K14: -0.089412671 | L14: 0.00064613995
B15: 完全成本加成率 | C15: [J]=[H]/[F] | D15: 0.037293196 | E15: 0.00064655771 | G15: 0.026564981 | H15: 0.0065554185 | K15: -0.082074198 | L15: 0.00064655772
B16: 毛利 | C16: [K]=[A]-[B] | D16: 1.3921808e+08 | E16: 1.4345095e+08 | G16: 1.4731733e+08 | H16: 1.7029582e+08 | K16: 4232870.5 | L16: 1.4345095e+08
B17: 贝里比率 | C17: [L]=[K]/([D]+[E]) | D17: 1.2279265 | E17: 1.0177012 | G17: 1.2185263 | H17: 1.0670262 | K17: 0.15347997 | L17: 1.0177012
B19: 成本加成 | C19: 加成率=A/B-1 | E19: 0.17825663 | G19: 0.18394488
