Workbook
Name \A: #REF!
Name \A: #REF!
Name _: '[1]046 Fixed Ass. mov.'!#REF!
Name __PC1: '[2]Physical Count'!$A$1:$B$65536
Name _CRA: '[3]U40'!#REF!
Name _CRA: '[3]U40'!#REF!
Name _DAT5: [4]SFG_ND!#REF!
Name _DAT7: [4]SFG_ND!#REF!
Name _DAT8: [4]SFG_ND!#REF!
Name _ftn1: '3 分部财务数据'!#REF!
Name _ftnref1: '3 分部财务数据'!#REF!
Name _W_DMOP_Billing_report_Jul_02: #REF!
Name A: #REF!
Name A: #REF!
Name aa: #REF!
Name aaa: #REF!
Name ACCOUNT: [5]Bank!$C$2:$C$99
Name AccountDesc: [6]Accounts!$A$1:$A$386
Name APTTL: [7]BKD!$N$573
Name AR: #REF!
Name AR: #REF!
Name AR_Summary_SGD_Currency: #REF!
Name AR_Summary_SGD_Currency: #REF!
Name AR_Summary_Source_Currency: #REF!
Name AR_Summary_Source_Currency: #REF!
Name ARUTL: #REF!
Name ARUTL: #REF!
Name as: [8]Input!$D$4
Name Automobiles: #REF!
Name b: #REF!
Name b: #REF!
Name brec0396: '[9]jun94'!#REF!
Name building: #REF!
Name Category: #REF!
Name Category: #REF!
Name CC: #REF!
Name CLIENT_NAME: #REF!
Name CNAME: [5]Bank!$B$2:$B$99
Name COA: #REF!
Name cost1: [2]Cost!$A$1:$P$65536
Name Cr: #REF!
Name Custom1: '[10]Drill-Down Lists'!$H$2:$H$3
Name Custom2: '[10]Drill-Down Lists'!$I$2:$I$544
Name Custom3: '[10]Drill-Down Lists'!$J$2:$J$3
Name Custom4: '[10]Drill-Down Lists'!$K$2:$K$3
Name Customer_Master_File: #REF!
Name Customer_Master_File: #REF!
Name CYCLES: [11]JobDetails!$A$56:$A$90
Name Database: #REF!
Name dfd: #REF!
Name Doubt_Debt: #REF!
Name Doubt_Debt: #REF!
Name Dr: #REF!
Name e: #REF!
Name e_data: OFFSET(#REF!,1,0,COUNTA(#REF!)-1,2)
Name e_empindex: #REF!
Name ee: #REF!
Name eeeefffff: '[1]046 Fixed Ass. mov.'!#REF!
Name Electrical: #REF!
Name ENAME: [5]Bank!$A$2:$A$99

Sheet 数据表
A1: 企业名称 | B1: ='1 组织结构及管理架构'!A1 -> 斯必克（上海）流体技术有限公司
A2: 年度 | B2: {=RIGHT(LEFT('3 分部财务数据'!A5:F5,8),2)} -> 24
A3: 事务所名称 | B3: =资料清单!A5 -> 立信税务师事务所有限公司
A4: 事务所简称 | B4: =资料清单!A6 -> 立信税务
A5: 企业简称 | B5: =资料清单!A7 -> 斯必克流体技术
A6: 母公司全称 | B6: =资料清单!A8 -> 斯必克投资
A7: 集团情况描述 | B7: =集团背景情况!A1 -> 使用kimi生成约500字的集团介绍
A8: 公司经营背景资料 | B8: =公司经营背景资料!A1 -> 根据企业访谈进行整理。

Sheet 集团背景情况
A1: 使用kimi生成约500字的集团介绍

Sheet 公司经营背景资料
A1: 根据企业访谈进行整理。

Sheet 主要产品
A1: 产品 | B1: 销售额（万元） | C1: 占比 (%)
A2: 产品A
A3: 产品B
A4: 产品C

Sheet 行业情况
A1: 3.1. 全球行业情况 | B1: kimi自动生成2000字
A2: 3.2. 中国行业情况 | B2: kimi自动生成2000字
A3: 3.3. 行业竞争情况 | B3: kimi自动生成2000字
A4: 3.4. 行业政策情况及未来趋势 | B4: kimi自动生成2000字
A5: 3.5. 小结 | B5: kimi生成500字总结

Sheet 被测关联交易
A1: 被测关联交易利润水平

Sheet 资料清单
A1: 【年度】年度转让定价同期资料准备所需基础资料和文件清单
A4: 敬请注意，该“提供资料清单”只适用于【企业名称】（以下简称“公司简称”）。贵公司需要提供截至【年度】会计年度12月31日（以下简称“【年度】年度”）的信息与资料，敬请贵公司注意，该清单是基于本所目前对贵公司经营状况的理解，该“资料清单”并不是全面的或是最终的，必要时我们会继续要求贵公司提供额外的信息和资料。我们希望贵公司能够尽量以电子表格的形式提供数据。对于较难获得或者以现场讨论的方式更易获取的信息，我们将在访谈时与贵公司进行探讨。 如果贵公司有任何的问题或建议，请联系我们的团队成员： 【事务所名称】 Project Manager: Tel: | Email: Tax Senior Consultant: Tel: (086) | Email:
A5: 立信税务师事务所有限公司
A6: 立信税务
A7: 斯必克流体技术
A8: 斯必克投资
A9: 资料清单 | B9: 附注
A10: I. 基本信息
A11: 1. 中华人民共和国企业法人营业执照 | B11: 如有更新请提供
A12: 2. 组织结构，包括企业各职能部门的设置、职责范围和雇员数量等（请提供截至【年度】年12月31日时点的组织结构图） | B12: 请见附件1
A13: 3. 管理架构，包括企业各级管理层的汇报对象以及汇报对象主要办公所在地等（请提供截至【年度】年12月31日时点的信息）
A14: 4. 【年度】年度关联公司信息 | B14: 请见附件2
A15: II. 财务信息
A16: 1. 【年度】年审计报告，包括经审计的财务报表及其附注 | B16: 请提供
A17: 2. 【年度】年度分部财务数据分析表，需包括企业不同类型产品的收入、成本、费用及利润。 | B17: 请见附件3
A18: 3. 【年度】年度《中华人民共和国企业年度关联业务往来报告表(2016年版)》 | B18: 请提供电子版
A19: 4. 【年度】年度贵公司主要关联供应商名单 | B19: 请见附件4
A20: 5. 【年度】年度的主要关联客户清单 | B20: 请见附件5
A21: 6. 【年度】年度其他关联交易类型、金额（如涉及） | B21: 如涉及，请提供

Sheet 1 组织结构及管理架构
A1: 斯必克（上海）流体技术有限公司
A3: 附件一：组织结构及管理架构
A5: 下表是我们根据【上年度】同期资料文档填写，还请贵公司更新截至【年度】年12月31日的部门信息和组织架构信息
A6: 主要部门 | B6: 人数 （截至【年度】年12月31日） | C6: 主要职责范围 | D6: 部门负责人汇报对象
D7: 汇报对象 | E7: 汇报对象主要办公所在地
A8: AAA | B8: 15 | C8: AAA | D8: CCC | E8: EEE
A9: BBB | B9: 16 | C9: BBB | D9: DDD | E9: FFF | F9: 新增
A23: 总计 | B23: =SUM(B8:B22) -> 31
A25: 请在此提供组织架构图：

Sheet 2 关联公司信息
A1: ='1 组织结构及管理架构'!A1 -> 斯必克（上海）流体技术有限公司
A3: 附件二：关联方相关信息
A4: 下表是我们根据【上年度】同期资料文档填写，请贵公司就【年度】年度情况对以下描述进行确认或更新。
A5: 行次 | B5: 关联方名称 | C5: 关联方类型 | D5: 国家（地区） | E5: 纳税人证件类型 | F5: 证件号 | G5: 关联关系类型 | H5: 起始日期 | I5: 截止日期 | J5: 法定税率 | K5: 是否享受税收优惠
B6: 1 | C6: 2 | D6: 3 | E6: 4 | F6: 5 | G6: 6 | H6: 7 | I6: 8 | J6: 9 | K6: 10
A7: 1 | B7: KKKK | C7: A | D7: B | E7: KKKK | F7: A | G7: B | H7: KKKK | I7: A | J7: B | K7: 否
C8: 0.0435 | D8: 0.005
C9: 0.0435 | D9: 0.005
C10: 0.0435 | D10: 0.005
C11: 0.0435 | D11: 0.005
C12: 0.0435 | D12: 0.005
C13: 0.0435 | D13: 0.005
A14: 2 | B14: 2 | C14: 0.0435 | D14: 0.005
A15: 2 | B15: 2 | C15: 0.0435 | D15: 0.005
A16: 2 | B16: 2 | C16: 0.0435 | D16: 0.005
A17: 注：
B18: “关联关系类型”：根据实际情况按以下关联关系标准选填代码A、B、C等，有多个关联关系类型的，应当选填多个代码。关联关系标准如下： A．一方直接或者间接持有另一方的股份总和达到25%以上；双方直接或者间接同为第三方所持有的股份达到25%以上。 如果一方通过中间方对另一方间接持有股份，只要其对中间方持股比例达到25%以上，则其对另一方的持股比例按照中间方对另一方的持股比例计算。 两个以上具有夫妻、直系血亲、兄弟姐妹以及其他抚养、赡养关系的自然人共同持股同一企业，持股比例合并计算。 B.双方存在持股关系或者同为第三方持股，虽持股比例未达到A项规定，但双方之间借贷资金总额占任一方实收资本比例达到50%以上，或者一方全部借贷资金总额的10%以上由另一方担保，与独立金融机构之间的借贷或者担保除外。 借贷资金总额占实收资本比例=年度加权平均借贷资金/年度加权平均实收资本，其中： - 年度加权平均借贷资金= i笔借入或者贷出资金账面金额×i笔借入或者贷出资金年度实际占用天数/365 - 年度加权平均实收资本= i笔实收资本账面金额×i笔实收资本年度实际占用天数/365 C.双方存在持股关系或者同为第三方持股，虽持股比例未达到A项规定，但一方的生产经营活动必须由另一方提供专利权、非专利技术、商标权、著作权等特许权才能正常进行。 D.双方存在持股关系或者同为第三方持股，虽持股比例未达到A项规定，但一方的购买、销售、接受劳务、提供劳务等经营活动由另一方控制。 上述控制是指一方有权决定另一方的财务和经营政策，并能据以从另一方的经营活动中获取利益。 E.一方半数以上董事或者半数以上高级管理人员（包括上市公司董事会秘书、经理、副经理、财务负责人和公司章程规定的其他人员）由另一方任命或者委派，或者同时担任另一方的董事或者高级管理人员；或者双方各自半数以上董事或者半数以上高级管理人员同为第三方任命或者委派。 F.具有夫妻、直系血亲、兄弟姐妹以及其他抚养、赡养关系的两个自然人分别与双方具有A至E项关系之一。 G.双方在实质上具有其他共同利益的关系。 除B项规定外，上述关联关系年度内发生变化的，按照实际关联关系存续期间认定。 仅因国家持股或者由国有资产管理部门委派董事、高级管理人员而存在A至E项关系的，不构成关联关系。 另外第7列“起始日期”和第8列“截止日期”：本报告年度所属期间内关联关系发生变化的，填报实际变化的日期；未发生变化的，填报本报告年度起始和截止日期。

Sheet 关联方个人信息
A1: 个人关联方 | B1: 国籍 | C1: 关联关系类型 | D1: 居住地址

Sheet 关联关系变化情况
A1: 关联方名称 | B1: 国家/地区 | C1: 关联关系类型 | D1: 起止日期 | E1: 变化原因
A2: UIUIUIU | B2: US | C2: AA | D2: 46023 | E2: 新增，自【清单模板-数据表B2】年3月1日起，XX有限公司收购本企业51%股权，与本企业构成关联关系
A3: UIUIUIU | B3: EU | C3: BB | D3: 46023 | E3: 减少，自【清单模板-数据表B2】年6月15日起，YY公司出售本企业全部股权，与本企业不构成关联关系

Sheet 3 分部财务数据
A1: ='1 组织结构及管理架构'!A1 -> 斯必克（上海）流体技术有限公司
A3: 附件三：分部财务数据
A5: 请贵公司就【24年度】情况对以下描述进行确认或更新。 | K5: 单位：人民币元
A6: 项目 | B6: 备注 | C6: 贸易业务 | G6: 其他业务（如有） | K6: 合计
C7: 境外 | E7: 境内 | G7: 境外 | I7: 境内
C8: 关联方 | D8: 非关联方 | E8: 关联方 | F8: 非关联方 | G8: 关联方 | H8: 非关联方 | I8: 关联方 | J8: 非关联方
A10: 一、营业收入
A11: 其中：主营业务收入
A12: 减：营业成本
A13: 其中：主营业务成本
A14: 营业税金及附加
A15: 其中：主营业务税金及附加
A16: 销售费用
A17: 管理费用
A18: 财务费用
A19: 资产减值损失
A20: 加：公允价值变动收益（损失以“-”号填列）
A21: 投资收益（损失以“-”号填列）
... A27: 说明：分别披露关联交易和非关联交易的收入、成本、费用和利润，不能直接归集的，按照合理比例划分，并说明该划分比例的依据。

Sheet 关联交易汇总表
A1: 关联交易类型 | B1: 境外交易金额 | C1: 境内交易金额 | D1: 交易总额
B2: A | C2: B | D2: C=A+B
A3: {有形资产所有权出让} | B3: 123 | C3: 456 | D3: =SUM(B3:C3) -> 579
A4: {有形资产所有权受让}
A5: {提供关联劳务}
A6: {接受关联劳务}
A7: ……
A8: {关联融资利息收入/支出}
A9: 合计

Sheet 4 供应商清单
A1: ='1 组织结构及管理架构'!A1 -> 斯必克（上海）流体技术有限公司
A3: 附件四： 供应商清单
A4: 请贵公司提供截至【年度】年12月31日包括关联方在内的贵公司的主要供应商详情。 请注明供应商位于境内还是境外、采购的产品类型、采购金额及每个供应商的采购金额占贵公司采购总金额的比例等。
A5: 项目 | B5: 编号 | C5: 供应商名称 | D5: 产品类型（例如原材料，半成品或成品） | E5: 会计年度【年度】 | H5: 运输条款（例如FOB，CIF等） | I5: 支付货币 （例如美元） | J5: 支付条款（例如发票开具日期30天内）
E6: 金额 （人民币） | F6: 占采购总金额比例 | G6: 占关联采购总金额比例
A7: 关联供应商
A8: 境外关联采购 | B8: 1 | C8: KKK | D8: sss | E8: 100
B9: 2
B10: 3
B11: 4
B12: 5
B13: 其他
B14: 境外关联采购小计 | E14: =SUM(E8:E13) -> 100 | F14: =IFERROR(E14/E$39,0) -> 1 | G14: =IFERROR(E14/E$22,0) -> 1
A15: 境内关联采购 | B15: 1
B16: 2
B17: 3
B18: 4
B19: 5
B20: 其他
B21: 境内关联采购小计 | E21: =SUM(E15:E20) -> 0 | F21: =IFERROR(E21/E$39,0) -> 0 | G21: =IFERROR(E21/E$22,0) -> 0
A22: 关联采购小计 | E22: =SUM(E14,E21) -> 100 | F22: =IFERROR(E22/E$39,0) -> 1 | G22: =IFERROR(E22/E$22,0) -> 1
A23: 非关联供应商
A24: 境外非关联采购 | B24: 1
B25: 2
B26: 3
B27: 4
B28: 5
B29: 其他
B30: 境外非关联采购小计 | E30: =SUM(E24:E29) -> 0 | F30: =IFERROR(E30/E$39,0) -> 0
A31: 境内非关联采购 | B31: 1
B32: 2
B33: 3
B34: 4
B35: 5
B36: 其他
B37: 境内非关联采购小计 | E37: =SUM(E31:E36) -> 0 | F37: =IFERROR(E37/E$39,0) -> 0
A38: 非关联采购小计 | E38: =SUM(E30,E37) -> 0 | F38: =IFERROR(E38/E$39,0) -> 0
A39: 合计 | E39: =SUM(E22,E38) -> 100 | F39: =IFERROR(E39/E$39,0) -> 1

Sheet 5 客户清单
A1: ='1 组织结构及管理架构'!A1 -> 斯必克（上海）流体技术有限公司
A3: 附件五：客户清单
A5: 请贵公司提供截至【年度】年12月31日包括关联方在内的贵公司的主要客户详情。 请注明客户位于境内还是境外、相关的产品类型、销售收入及每个客户的销售收入占贵公司销售总收入的比例等。
A6: 项目 | B6: 编号 | C6: 客户名称 | D6: 产品以及产品细分（例如A1，B2等） | E6: 会计年度【年度】 | H6: 运输条款（例如FOB，CIF等） | I6: 支付货币 （例如美元） | J6: 支付条款（例如发票开具日期30天内）
E7: 金额 （人民币） | F7: 占销售总收入比例 | G7: 占关联销售总收入比例
A8: 关联客户
A9: 境外关联销售 | B9: 1 | C9: BBB | D9: CC | E9: 6000
B10: 2
B11: 3
B12: 4
B13: 5
B14: 其他
B15: 境外关联销售小计 | E15: =SUBTOTAL(9,E9:E14) -> 6000 | F15: =IFERROR(E15/E$40,0) -> 1 | G15: =IFERROR(E15/E$23,0) -> 1
A16: 境内关联销售 | B16: 1
B17: 2
B18: 3
B19: 4
B20: 5
B21: 其他
B22: 境内关联销售小计 | E22: =SUBTOTAL(9,E16:E21) -> 0 | F22: =IFERROR(E22/E$40,0) -> 0 | G22: =IFERROR(E22/E$23,0) -> 0
A23: 关联销售小计 | E23: =SUBTOTAL(9,E9:E22) -> 6000 | F23: =IFERROR(E23/E$40,0) -> 1 | G23: =IFERROR(E23/E$23,0) -> 1
A24: 非关联客户
A25: 境外非关联销售 | B25: 1
B26: 2
B27: 3
B28: 4
B29: 5
B30: 其他
B31: 境外非关联销售小计 | E31: =SUBTOTAL(9,E25:E30) -> 0 | F31: =IFERROR(E31/E$40,0) -> 0 | G31: =IFERROR(E31/E$39,0) -> 0
A32: 境内非关联销售 | B32: 1
B33: 2
B34: 3
B35: 4
B36: 5
B37: 其他
B38: 境内非关联销售小计 | E38: =SUBTOTAL(9,E32:E37) -> 0 | F38: =IFERROR(E38/E$40,0) -> 0 | G38: =IFERROR(E38/E$39,0) -> 0
A39: 非关联销售小计 | E39: =SUBTOTAL(9,E25:E38) -> 0 | F39: =IFERROR(E39/E$40,0) -> 0 | G39: =IFERROR(E39/E$39,0) -> 0
A40: 合计 | E40: =SUM(E23,E39) -> 6000 | F40: =IFERROR(E40/E$40,0) -> 1

Sheet 6 劳务交易表
A3: 附件六：劳务交易表
A5: 请贵公司提供截至2019年12月31日贵公司的关联劳务交易详情。
A6: 行次 | B6: 关联交易类型 | C6: 关联方名称 | D6: 关联交易内容 | E6: 交易金额 | F6: 比例 | G6: 占总劳务收入比重（%）
B8: 1 | C8: 2 | D8: 3 | E8: 4 | F8: 5 | G8: 6
A9: 1 | B9: 境外关联 劳务收入 | C9: SPX AA | D9: ss | E9: 5000
A10: 2
A11: 3
A12: 4
A13: 5
A14: 6 | B14: ──── | C14: 其他关联方 | D14: ────
A15: 7 | B15: 境外关联劳务收入小计 | E15: =ROUND(SUM(E9:E14),2) -> 5000
A16: 8 | B16: 境内关联 劳务收入
A17: 9
A18: 10
A19: 11
A20: 12
A21: 13 | B21: ──── | C21: 其他关联方 | D21: ────
A22: 14 | B22: 境内关联劳务收入小计 | E22: =ROUND(SUM(E16:E21),2) -> 0
A23: 15 | B23: 境内外关联和非关联劳务收入合计
A24: 16 | B24: 境外关联 劳务支出
A25: 17
A26: 18
A27: 19
A28: 20
A29: 21 | B29: ──── | C29: 其他关联方 | D29: ────
A30: 22 | B30: 境外关联劳务支出小计 | E30: =ROUND(SUM(E24:E29),2) -> 0
A31: 23 | B31: 境内关联 劳务支出
A32: 24
A33: 25
A34: 26
A35: 27
A36: 28 | B36: ──── | C36: 其他关联方 | D36: ────
A37: 29 | B37: 境内关联劳务支出小计 | E37: =ROUND(SUM(E31:E36),2) -> 0
A38: 30 | B38: 境内外关联和非关联劳务支出合计

Sheet 劳务成本归集
A1: 劳务内容 | B1: 分配方法 | C1: 总成本费用 | D1: 【清单模板-数据表B5】
D2: 所需承担的比例
A3: 市场营销服务 | B3: 销售额 | C3: XX,XXX | D3: XX%
A4: 行政支持服务 | B4: 销售额 | C4: XX,XXX | D4: XX%
A5: 信息技术服务 | B5: 人数 | C5: XX,XXX | D5: XX%

Sheet 资金融通
A1: 关联方 | B1: 金额
A4: 合计

Sheet 公司间资金融通交易总结
A1: 缔约方 | B1: 公司间资金融通交易性质 | C1: 货币 | D1: 本金 | E1: 本金 | F1: 到期期限 | G1: 利率 | H1: 利息收入/利息支出 | I1: 利息收入/利息支出
D2: （原币） | E2: （人民币） | H2: （原币） | I2: （人民币）
B3: 借款/贷款

Sheet 有形资产信息
A1: 资产净值 | B1: 年初数 | C1: 年末数
A2: 房屋及建筑物
A3: 电脑设备
A4: 机器设备
A5: 办公设备
A6: 家具
A7: 运输设备
A8: 生产设备
A9: 其他
A10: 合计

Sheet 功能风险汇总表
A1: 序号 | B1: 风险 | C1: 【清单模板-数据表B5】 | D1: 关联方
A2: 1
A3: 2
A4: 3

Sheet PL
A2: 项目 | B2: 公式 | C2: 【年度】
A4: 营业收入 | B4: a | C4: 1000
A5: 减：营业成本 | B5: b | C5: 200
A6: 税金及附加 | B6: c | C6: 3000
A7: 营业利润 | B7: d = a-b-c | C7: =C4-C5-C6 -> -2200
A8: 减：销售费用 | B8: e | C8: 200
A9: 管理费用 | B9: f | C9: 300
A10: 息税前利润 | B10: g = a-b-c-e-f | C10: =C7-C8-C9 -> -2700
A11: 营业成本及费用 | B11: h = b+c+e+f | C11: =C5+C6+C8+C9 -> 3700
A12: 完全成本加成率 | B12: i= g/h | C12: =C10/C11 -> -0.72972973
A16: 根据访谈，关联销售以审计报告为准
A18: 境外关联销售 | B18: 1
B19: 2
B20: 3
B21: 4
B22: 5
B23: 其他
B24: 境外关联销售小计 | E24: =SUBTOTAL(9,E18:E23) -> 0
A25: 境内关联销售 | B25: 1
B26: 2
B27: 3
B28: 4
B29: 5
B30: 其他
B31: 境内关联销售小计 | E31: =SUBTOTAL(9,E25:E30) -> 0
A47: 关联交易类型 | B47: 境外交易金额 | C47: 境内交易金额 | D47: 交易总额
B48: A | C48: B | D48: C=A+B
A49: 关联采购
A50: 关联销售
A51: 总计 | B51: =SUM(B49:B50) -> 0
A56: 关联方名称 | C56: 交易金额 | D56: 占采购、销售总额比例(%)
A57: 关联
A58: 采购
A59: 关联采购总计
A60: 关联
A61: 销售
A63: 关联销售总计

Sheet PL含特殊因素调整
